obapi/__init__.py
obapi/_version.py
obapi/admin.py
obapi/api.py
obapi/apps.py
obapi/assemble.py
obapi/converters.py
obapi/download.py
obapi/exceptions.py
obapi/export.py
obapi/formfields.py
obapi/forms.py
obapi/modelfields.py
obapi/tidy.py
obapi/urls.py
obapi/utils.py
obapi/validators.py
obapi/migrations/0001_initial.py
obapi/migrations/0002_alter_contentitem_download_timestamp_and_more.py
obapi/migrations/0003_alter_contentitem_title_and_more.py
obapi/migrations/0004_essaycontentitem.py
obapi/migrations/0005_sequence_create_timestamp_sequence_update_timestamp.py
obapi/migrations/0006_alter_sequence_options.py
obapi/migrations/0007_rename_text_html_textcontentitem_text_html_tmp_and_more.py
obapi/migrations/0008_alter_youtubecontentitem_yt_channel_title.py
obapi/migrations/0009_remove_description_fields.py
obapi/migrations/__init__.py
obapi/models/__init__.py
obapi/models/classifiers.py
obapi/models/content.py
obapi/models/sequence.py
obapi/templates/admin/obapi/add_form.html
obapi/templates/admin/obapi/obcontentitem/change_list.html
obapi/templates/obapi/export/contentitem.html
obapi/templates/obapi/export/essaycontentitem.html
obapi/templates/obapi/export/metadata.md
obapi/templates/obapi/export/obcontentitem.html
obapi/templates/obapi/export/spotifycontentitem.html
obapi/templates/obapi/export/youtubecontentitem.html
django_overcomingbias_api-0.6.3.dist-info/METADATA
django_overcomingbias_api-0.6.3.dist-info/WHEEL
django_overcomingbias_api-0.6.3.dist-info/licenses/LICENSE
django_overcomingbias_api-0.6.3.dist-info/RECORD
