Metadata-Version: 2.1
Name: django-overcomingbias-api
Version: 0.6.3
Summary: django-overcomingbias-api: an API to Robin Hanson's content
Project-URL: repository, https://github.com/chris-mcdo/django-overcomingbias-api
Project-URL: issues, https://github.com/chris-mcdo/django-overcomingbias-api/issues
Project-URL: documentation, https://django-overcomingbias-api.readthedocs.io/en/stable
Project-URL: changelog, https://django-overcomingbias-api.readthedocs.io/en/stable/changelog.html
Author-email: Christopher McDonald <cmcdonal33@gmail.com>
License: MIT License
License-File: LICENSE
Keywords: api,django,overcomingbias,scrape
Classifier: Development Status :: 4 - Beta
Classifier: Environment :: Web Environment
Classifier: Framework :: Django
Classifier: Framework :: Django :: 4
Classifier: Intended Audience :: Developers
Classifier: License :: OSI Approved :: MIT License
Classifier: Operating System :: MacOS :: MacOS X
Classifier: Operating System :: Microsoft :: Windows
Classifier: Operating System :: POSIX
Classifier: Programming Language :: Python :: 3
Classifier: Programming Language :: Python :: 3 :: Only
Classifier: Programming Language :: Python :: 3.8
Classifier: Programming Language :: Python :: 3.9
Classifier: Programming Language :: Python :: 3.10
Classifier: Topic :: Internet
Classifier: Topic :: Internet :: WWW/HTTP
Classifier: Topic :: Internet :: WWW/HTTP :: Dynamic Content
Classifier: Topic :: Internet :: WWW/HTTP :: Indexing/Search
Requires-Python: >=3.8
Requires-Dist: bleach>=5.0.0
Requires-Dist: django-model-utils>=4.2.0
Requires-Dist: django-ninja
Requires-Dist: django-ordered-model>=3.5
Requires-Dist: django<5.0,>=4.0
Requires-Dist: obscraper
Requires-Dist: pandadoc
Requires-Dist: python-dateutil>=2.7
Requires-Dist: python-slugify>=5.0
Provides-Extra: test
Requires-Dist: pytest-django>=4.5.0; extra == 'test'
Requires-Dist: pytest>=6.2.5; extra == 'test'
Requires-Dist: python-dotenv>=0.20.0; extra == 'test'
